pyaws/DynamoDB.py
pyaws/S3.py
pyaws/SQS.py
pyaws/__init__.py
pyaws/structs.py
aws_easy_tool-0.6.0.dist-info/LICENSE
aws_easy_tool-0.6.0.dist-info/METADATA
aws_easy_tool-0.6.0.dist-info/WHEEL
aws_easy_tool-0.6.0.dist-info/entry_points.txt
aws_easy_tool-0.6.0.dist-info/top_level.txt
aws_easy_tool-0.6.0.dist-info/RECORD
