Metadata-Version: 2.1
Name: aws_easy_tool
Version: 0.6.0
Summary: A Python package to facilitate daily tasks when using AWS.
Home-page: https://github.com/mbenencase/py-aws
Author: Marcelo Eduardo Benencase
Author-email: marcelo.benencase@gmail.com
Classifier: Programming Language :: Python :: 3
Classifier: License :: OSI Approved :: MIT License
Classifier: Operating System :: OS Independent
License-File: LICENSE
Requires-Dist: boto3
Requires-Dist: pydantic
Requires-Dist: pydantic-settings
Requires-Dist: tqdm
